dispytch/__init__.py
dispytch/di/__init__.py
dispytch/di/builder.py
dispytch/di/context.py
dispytch/di/dependency.py
dispytch/di/event.py
dispytch/di/exc.py
dispytch/di/extractor.py
dispytch/di/solver.py
dispytch/di/topic_segment.py
dispytch/di/tree.py
dispytch/emitter/__init__.py
dispytch/emitter/emitter.py
dispytch/emitter/event.py
dispytch/emitter/producer.py
dispytch/kafka/__init__.py
dispytch/kafka/consumer.py
dispytch/kafka/producer.py
dispytch/listener/__init__.py
dispytch/listener/consumer.py
dispytch/listener/handler.py
dispytch/listener/handler_group.py
dispytch/listener/handler_tree.py
dispytch/listener/listener.py
dispytch/rabbitmq/__init__.py
dispytch/rabbitmq/consumer.py
dispytch/rabbitmq/producer.py
dispytch/redis/__init__.py
dispytch/redis/consumer.py
dispytch/redis/producer.py
dispytch/serialization/__init__.py
dispytch/serialization/deserializer.py
dispytch/serialization/errors.py
dispytch/serialization/serializer.py
dispytch/serialization/validator.py
dispytch/serialization/json/__init__.py
dispytch/serialization/json/deserializer.py
dispytch/serialization/json/serializer.py
dispytch/serialization/msgpack/__init__.py
dispytch/serialization/msgpack/deserializer.py
dispytch/serialization/msgpack/serializer.py
dispytch-0.10.1.dist-info/METADATA
dispytch-0.10.1.dist-info/WHEEL
dispytch-0.10.1.dist-info/licenses/LICENSE
dispytch-0.10.1.dist-info/RECORD
