Metadata-Version: 2.4
Name: dispytch
Version: 0.10.1
Summary: Lightweight Python framework for writing clean and testable event-driven services
Author: Ivan Mihun
License-File: LICENSE
Requires-Python: >=3.13
Requires-Dist: pydantic>=2.11.7
Provides-Extra: kafka
Requires-Dist: aiokafka>=0.12.0; extra == 'kafka'
Provides-Extra: msgpack
Requires-Dist: msgpack>=1.1.1; extra == 'msgpack'
Provides-Extra: rabbitmq
Requires-Dist: aio-pika>=9.5.5; extra == 'rabbitmq'
Provides-Extra: redis
Requires-Dist: redis>=6.2.0; extra == 'redis'
